django_responseblock-0.2.0.dist-info/DESCRIPTION.rst
django_responseblock-0.2.0.dist-info/METADATA
django_responseblock-0.2.0.dist-info/RECORD
django_responseblock-0.2.0.dist-info/WHEEL
django_responseblock-0.2.0.dist-info/metadata.json
django_responseblock-0.2.0.dist-info/top_level.txt
responseblock/__init__.py
responseblock/admin.py
responseblock/models.py
