Metadata-Version: 2.0
Name: django-responseblock
Version: 0.2.0
Summary: display a user's response
Home-page: UNKNOWN
Author: Anders Pearson
Author-email: anders@columbia.edu
License: BSD
Platform: any
